flake8_fancy_header/__init__.py
flake8_fancy_header/checker.py
flake8_fancy_header-0.3.0.dist-info/LICENSE
flake8_fancy_header-0.3.0.dist-info/METADATA
flake8_fancy_header-0.3.0.dist-info/WHEEL
flake8_fancy_header-0.3.0.dist-info/entry_points.txt
flake8_fancy_header-0.3.0.dist-info/top_level.txt
flake8_fancy_header-0.3.0.dist-info/RECORD
