Metadata-Version: 2.1
Name: flake8-fancy-header
Version: 0.3.0
Summary: check file has a fancy header at the top
Home-page: https://github.com/yevhen-m/flake8-fancy-header
Author: yevhen-m
Author-email: UNKNOWN
License: MIT
Platform: UNKNOWN
Classifier: Framework :: Flake8
Classifier: Environment :: Console
Classifier: Intended Audience :: Developers
Classifier: License :: OSI Approved :: MIT License
Classifier: Programming Language :: Python
Classifier: Programming Language :: Python :: 2
Classifier: Programming Language :: Python :: 3
Classifier: Topic :: Software Development :: Libraries :: Python Modules
Classifier: Topic :: Software Development :: Quality Assurance
Requires-Dist: flake8 (>3.0.0)
